{
	"mainpurpose": "Better diggy diggy hole!",
	"code": "minerz:reinforced-pickaxe",
	"storageFlags": 5,
	"attributes": {
		"heldItemPitchFollow": 0.9,
		"handbook": {
			"include": true,
			"groupBy": ["reinforced-pickaxe-*"]
		},
		"toolrackTransform": {
			"rotation": { "y": 2.5, "z": -1 },
			"translation": { "x": -0.1, "y": 0.59 },
			"scale": 1.25
		},
		"groundStorageTransform": {
			"translation": { "x": 0, "y": 0.1, "z": -0.065 },
			"rotation": { "x": 20, "y": 88, "z": -87 },
			"scale": 0.88
		},
		"slotRefillIdentifier": "pickaxe"
	},
	"behaviors": [{ 
		"name": "GroundStorable",
		"properties": {
			"layout": "WallHalves",
			"wallOffY": 1,
			"sprintKey": true,
			"selectionBox": { "x1": 0, "y1": 0, "z1": 0, "x2": 1, "y2": 0.1, "z2": 1 },
			"collisionBox": { "x1": 0, "y1": 0, "z1": 0, "x2": 0, "y2": 0, "z2": 0 }
		}
	}],
	"variantgroups": [
		{"code": "wood", "states": ["oak", "walnut"]},
		{"code": "metal", "states": ["copper", "tinbronze", "bismuthbronze", "blackbronze", "gold", "silver", "iron", "meteoriciron", "steel"]}
	],
	"tool": "pickaxe",
	"damagedby": ["blockbreaking", "attacking"],
	"shape": { "base": "minerz:item/tool/reinforced-pickaxe" },
	"heldTpHitAnimation": "smithingwide",
	"texturesByType": {
		"*": {
			
			"wood": { "base": "game:block/wood/debarked/{wood}" },
			"metal": { "base": "game:block/metal/ingot/{metal}" }
		}
	},
	"tooltierbytype": {
		"*-copper": 2,
		"*-gold": 2,
		"*-silver": 2,
		"*-bismuthbronze": 3,
		"*-tinbronze": 3,
		"*-blackbronze": 3,
		"*-iron": 4,
		"*-meteoriciron": 4,
		"*-steel": 5
	},
	"miningspeedbytype": {
		"*-oak-copper": {
			"ceramic": 2,
			"stone": 5,
			"ore": 5,
			"metal": 5,
			"ice": 2
		},
		"*-oak-bismuthbronze": {
			"ceramic": 3,
			"stone": 6,
			"ore": 6,
			"metal": 6,
			"ice": 2.5
		},
		"*-oak-tinbronze": {
			"ceramic": 2.5,
			"stone": 7,
			"ore": 7,
			"metal": 7,
			"ice": 2.5
		},
		"*-oak-gold": {
			"ceramic": 2,
			"stone": 6,
			"ore": 6,
			"metal": 6,
			"ice": 2.5
		},
		"*-oak-silver": {
			"ceramic": 2,
			"stone": 6,
			"ore": 6,
			"metal": 6,
			"ice": 2.5
		},
		"*-oak-blackbronze": {
			"ceramic": 3,
			"stone": 7,
			"ore": 7,
			"metal": 7,
			"ice": 3
		},
		"*-oak-iron": {
			"ceramic": 3,
			"stone": 8,
			"ore": 8,
			"metal": 8,
			"ice": 8
		},
		"*-oak-meteoriciron": {
			"ceramic": 4,
			"stone": 9,
			"ore": 9,
			"metal": 9,
			"ice": 4
		},
		"*-oak-steel": {
			"ceramic": 4,
			"stone": 11,
			"ore": 12,
			"metal": 10,
			"ice": 5
		},
		"*-walnut-copper": {
			"ceramic": 2.3,
			"stone": 5.3,
			"ore": 5.3,
			"metal": 5.3,
			"ice": 2.3
		},
		"*-walnut-bismuthbronze": {
			"ceramic": 3.3,
			"stone": 6.3,
			"ore": 6.3,
			"metal": 6.3,
			"ice": 2.8
		},
		"*-walnut-tinbronze": {
			"ceramic": 2.8,
			"stone": 7.3,
			"ore": 7.3,
			"metal": 7.3,
			"ice": 2.8
		},
		"*-walnut-gold": {
			"ceramic": 2.3,
			"stone": 6.3,
			"ore": 6.3,
			"metal": 6.3,
			"ice": 2.8
		},
		"*-walnut-silver": {
			"ceramic": 2.3,
			"stone": 6.3,
			"ore": 6.3,
			"metal": 6.3,
			"ice": 2.8
		},
		"*-walnut-blackbronze": {
			"ceramic": 3.3,
			"stone": 7.3,
			"ore": 7.3,
			"metal": 7.3,
			"ice": 3.3
		},
		"*-walnut-iron": {
			"ceramic": 3.3,
			"stone": 8.3,
			"ore": 8.3,
			"metal": 8.3,
			"ice": 8.3
		},
		"*-walnut-meteoriciron": {
			"ceramic": 4.3,
			"stone": 9.3,
			"ore": 9.3,
			"metal": 9.3,
			"ice": 4.3
		},
		"*-walnut-steel": {
			"ceramic": 4.3,
			"stone": 11.3,
			"ore": 12.3,
			"metal": 10.3,
			"ice": 5.3
		}
	},
	"attackpowerbytype": {
		"*-oak-copper": 1.5,
		"*-oak-bismuthbronze": 2,
		"*-oak-tinbronze": 2,
		"*-oak-gold": 2,
		"*-oak-silver": 2,
		"*-oak-blackbronze": 2,
		"*-oak-iron": 3,
		"*-oak-meteoriciron": 3,
		"*-oak-steel": 3,
		"*-walnut-copper": 1.7,
		"*-walnut-bismuthbronze": 2.3,
		"*-walnut-tinbronze": 2.3,
		"*-walnut-gold": 2.3,
		"*-walnut-silver": 2.3,
		"*-walnut-blackbronze": 2.3,
		"*-walnut-iron": 3.3,
		"*-walnut-meteoriciron": 3.3,
		"*-walnut-steel": 3.3
	},
	"durabilitybytype": {
		"*-oak-gold": 270,
		"*-oak-silver": 310,
		"*-oak-copper": 525,
		"*-oak-tinbronze": 790,
		"*-oak-bismuthbronze": 875,
		"*-oak-blackbronze": 970,
		"*-oak-iron": 1750,
		"*-oak-meteoriciron": 2275,
		"*-oak-steel": 4375,
		"*-walnut-gold": 250,
		"*-walnut-silver": 300,
		"*-walnut-copper": 500,
		"*-walnut-tinbronze": 700,
		"*-walnut-bismuthbronze": 800,
		"*-walnut-blackbronze": 900,
		"*-walnut-iron": 1500,
		"*-walnut-meteoriciron": 2000,
		"*-walnut-steel": 4200
	},
	"creativeinventory": { "general": ["*"], "items": ["*"], "tools": ["*"] },
	"guiTransform": {
		"translation": { "x": 0, "y": 0, "z": 0 },
		"rotation": { "x": -89, "y": 47, "z": 33 },
		"origin": { "x": 0.61, "y": 0, "z": 0.47 },
		"scale": 1.7
	},
	"fpHandTransform": {
		"translation": { "x": -0.4, "y": -0.5, "z": 0.6 },
		"rotation": { "x": -35, "y": 0, "z": 85 },
		"origin": { "x": 0.1, "y": 0.5, "z": 0.5 },
		"scale": 2.5
	},
	"groundTransform": {
		"translation": { "x": 0, "y": 0, "z": 0 },
		"rotation": { "x": 0, "y": 0, "z": 0 },
		"origin": { "x": 0.5, "y": 0, "z": 0.5 },
		"scale": 3.4
	},
	"tpHandTransform": {
		"translation": { "x": -0.87, "y": -0.01, "z": -0.56 },
		"rotation": { "x": -90, "y": 0, "z": 0 },
		"origin": { "x": 0.5, "y": 0, "z": 0.5 },
		"scale": 0.8
	}
}